setup.py
boxwilddog/__init__.py
boxwilddog/boxwilddog.py
boxwilddog.egg-info/PKG-INFO
boxwilddog.egg-info/SOURCES.txt
boxwilddog.egg-info/dependency_links.txt
boxwilddog.egg-info/top_level.txt