Metadata-Version: 1.0
Name: boxwilddog
Version: 0.0.3
Summary: wilddog tool
Home-page: UNKNOWN
Author: CcdjhMarx
Author-email: ccdjh.marx@all.com
License: MIT License
Keywords: wilddog,json,db,value
Platform: UNKNOWN
